goodlogistic/__init__.py
goodlogistic/module.py
goodlogistic/core/__init__.py
goodlogistic/utils/__init__.py
tests/__init__.py
tests/test_module.py
goodlogistic-0.1.0.dist-info/LICENSE
goodlogistic-0.1.0.dist-info/METADATA
goodlogistic-0.1.0.dist-info/WHEEL
goodlogistic-0.1.0.dist-info/top_level.txt
goodlogistic-0.1.0.dist-info/RECORD
