Metadata-Version: 2.1
Name: goodlogistic
Version: 0.1.0
Summary: Toolkit for logistic problem, designed for real challenges Nonprofit organization.
Home-page: https://github.com/daftar/goodlogistic
Author: Rodrigo J. R Santos
Author-email: contato@goodtruck.org.br
License: UNKNOWN
Platform: UNKNOWN
Classifier: Programming Language :: Python :: 3
Classifier: License :: OSI Approved :: MIT License
Classifier: Operating System :: OS Independent
Requires-Python: >=3.8
